<?xml version="1.0"?>
<dc-workflow workflow_id="preliminary_notice_workflow"
             title="preliminary_notice_workflow"
             state_variable="review_state"
             initial_state="deposit"
             xmlns:i18n="http://xml.zope.org/namespaces/i18n"
             i18n:domain="plone">
 <permission>View</permission>
 <permission>Access contents information</permission>
 <permission>Delete objects</permission>
 <permission>Modify portal content</permission>
 <permission>Add portal content</permission>
 <permission>liege.urban: Validate</permission>
 <permission>liege.urban: External Reader</permission>
 <permission>urban: Add PortionOut</permission>
 <permission>urban: Add Contact</permission>
 <permission>urban: Add Applicant</permission>
 <permission>urban: Add UrbanEvent</permission>
 <permission>urban: Add Corporation</permission>
 <permission>ATContentTypes: Add File</permission>
 <permission>ATContentTypes: Add Image</permission>
 <state state_id="analysis"
        title="analysis"
        i18n:attributes="title">
  <exit-transition transition_id="propose_analysis"/>
  <exit-transition transition_id="go_back_1"/>
  <permission-map name="Access contents information"
                  acquired="False">
   <permission-role>Reader</permission-role>
   <permission-role>Editor</permission-role>
   <permission-role>Contributor</permission-role>
   <permission-role>Manager</permission-role>
  </permission-map>
  <permission-map name="ATContentTypes: Add File"
                  acquired="False">
   <permission-role>Editor</permission-role>
   <permission-role>Contributor</permission-role>
   <permission-role>Manager</permission-role>
  </permission-map>
  <permission-map name="ATContentTypes: Add Image"
                  acquired="False">
   <permission-role>Editor</permission-role>
   <permission-role>Contributor</permission-role>
   <permission-role>Manager</permission-role>
  </permission-map>
  <permission-map name="Add portal content"
                  acquired="False">
   <permission-role>Editor</permission-role>
   <permission-role>Contributor</permission-role>
   <permission-role>Manager</permission-role>
  </permission-map>
  <permission-map name="Delete objects"
                  acquired="False">
   <permission-role>Editor</permission-role>
   <permission-role>Contributor</permission-role>
   <permission-role>Manager</permission-role>
  </permission-map>
  <permission-map name="Modify portal content"
                  acquired="False">
   <permission-role>Editor</permission-role>
   <permission-role>Contributor</permission-role>
   <permission-role>Manager</permission-role>
  </permission-map>
  <permission-map name="View"
                  acquired="False">
   <permission-role>Reader</permission-role>
   <permission-role>Editor</permission-role>
   <permission-role>Contributor</permission-role>
   <permission-role>Manager</permission-role>
  </permission-map>
  <permission-map name="liege.urban: External Reader"
                  acquired="False">
   <permission-role>Reader</permission-role>
   <permission-role>Editor</permission-role>
   <permission-role>Contributor</permission-role>
   <permission-role>Manager</permission-role>
  </permission-map>
  <permission-map name="liege.urban: Validate"
                  acquired="False">
   <permission-role>Contributor</permission-role>
   <permission-role>Manager</permission-role>
  </permission-map>
  <permission-map name="urban: Add Applicant"
                  acquired="False">
   <permission-role>Editor</permission-role>
   <permission-role>Contributor</permission-role>
   <permission-role>Manager</permission-role>
  </permission-map>
  <permission-map name="urban: Add Contact"
                  acquired="False">
   <permission-role>Editor</permission-role>
   <permission-role>Contributor</permission-role>
   <permission-role>Manager</permission-role>
  </permission-map>
  <permission-map name="urban: Add Corporation"
                  acquired="False">
   <permission-role>Editor</permission-role>
   <permission-role>Contributor</permission-role>
   <permission-role>Manager</permission-role>
  </permission-map>
  <permission-map name="urban: Add PortionOut"
                  acquired="False">
   <permission-role>AddressEditor</permission-role>
   <permission-role>Manager</permission-role>
  </permission-map>
  <permission-map name="urban: Add UrbanEvent"
                  acquired="False">
   <permission-role>Editor</permission-role>
   <permission-role>Contributor</permission-role>
   <permission-role>Manager</permission-role>
  </permission-map>
 </state>
 <state state_id="analysis_validation"
        title="analysis_validation"
        i18n:attributes="title">
  <exit-transition transition_id="validate"/>
  <exit-transition transition_id="refuse_analysis"/>
  <permission-map name="Access contents information"
                  acquired="False">
   <permission-role>Reader</permission-role>
   <permission-role>Editor</permission-role>
   <permission-role>Contributor</permission-role>
   <permission-role>Manager</permission-role>
  </permission-map>
  <permission-map name="ATContentTypes: Add File"
                  acquired="False">
   <permission-role>Editor</permission-role>
   <permission-role>Contributor</permission-role>
   <permission-role>Manager</permission-role>
  </permission-map>
  <permission-map name="ATContentTypes: Add Image"
                  acquired="False">
   <permission-role>Editor</permission-role>
   <permission-role>Contributor</permission-role>
   <permission-role>Manager</permission-role>
  </permission-map>
  <permission-map name="Add portal content"
                  acquired="False">
   <permission-role>Editor</permission-role>
   <permission-role>Contributor</permission-role>
   <permission-role>Manager</permission-role>
  </permission-map>
  <permission-map name="Delete objects"
                  acquired="False">
   <permission-role>Editor</permission-role>
   <permission-role>Contributor</permission-role>
   <permission-role>Manager</permission-role>
  </permission-map>
  <permission-map name="Modify portal content"
                  acquired="False">
   <permission-role>Editor</permission-role>
   <permission-role>Contributor</permission-role>
   <permission-role>Manager</permission-role>
  </permission-map>
  <permission-map name="View"
                  acquired="False">
   <permission-role>Reader</permission-role>
   <permission-role>Editor</permission-role>
   <permission-role>Contributor</permission-role>
   <permission-role>Manager</permission-role>
  </permission-map>
  <permission-map name="liege.urban: External Reader"
                  acquired="False">
   <permission-role>Reader</permission-role>
   <permission-role>Editor</permission-role>
   <permission-role>Contributor</permission-role>
   <permission-role>Manager</permission-role>
  </permission-map>
  <permission-map name="liege.urban: Validate"
                  acquired="False">
   <permission-role>Contributor</permission-role>
   <permission-role>Manager</permission-role>
  </permission-map>
  <permission-map name="urban: Add Applicant"
                  acquired="False">
   <permission-role>Editor</permission-role>
   <permission-role>Contributor</permission-role>
   <permission-role>Manager</permission-role>
  </permission-map>
  <permission-map name="urban: Add Contact"
                  acquired="False">
   <permission-role>Editor</permission-role>
   <permission-role>Contributor</permission-role>
   <permission-role>Manager</permission-role>
  </permission-map>
  <permission-map name="urban: Add Corporation"
                  acquired="False">
   <permission-role>Editor</permission-role>
   <permission-role>Contributor</permission-role>
   <permission-role>Manager</permission-role>
  </permission-map>
  <permission-map name="urban: Add PortionOut"
                  acquired="False">
   <permission-role>AddressEditor</permission-role>
   <permission-role>Manager</permission-role>
  </permission-map>
  <permission-map name="urban: Add UrbanEvent"
                  acquired="False">
   <permission-role>Editor</permission-role>
   <permission-role>Contributor</permission-role>
   <permission-role>Manager</permission-role>
  </permission-map>
 </state>
 <state state_id="college"
        title="college"
        i18n:attributes="title">
  <exit-transition transition_id="close_favorable"/>
  <exit-transition transition_id="go_back_2"/>
  <exit-transition transition_id="close_defavorable"/>
  <permission-map name="Access contents information"
                  acquired="False">
   <permission-role>Reader</permission-role>
   <permission-role>Editor</permission-role>
   <permission-role>Contributor</permission-role>
   <permission-role>Manager</permission-role>
  </permission-map>
  <permission-map name="ATContentTypes: Add File"
                  acquired="False">
   <permission-role>Editor</permission-role>
   <permission-role>Contributor</permission-role>
   <permission-role>Manager</permission-role>
  </permission-map>
  <permission-map name="ATContentTypes: Add Image"
                  acquired="False">
   <permission-role>Editor</permission-role>
   <permission-role>Contributor</permission-role>
   <permission-role>Manager</permission-role>
  </permission-map>
  <permission-map name="Add portal content"
                  acquired="False">
   <permission-role>Editor</permission-role>
   <permission-role>Contributor</permission-role>
   <permission-role>Manager</permission-role>
  </permission-map>
  <permission-map name="Delete objects"
                  acquired="False">
   <permission-role>Editor</permission-role>
   <permission-role>Contributor</permission-role>
   <permission-role>Manager</permission-role>
  </permission-map>
  <permission-map name="Modify portal content"
                  acquired="False">
   <permission-role>Editor</permission-role>
   <permission-role>Contributor</permission-role>
   <permission-role>Manager</permission-role>
  </permission-map>
  <permission-map name="View"
                  acquired="False">
   <permission-role>Reader</permission-role>
   <permission-role>Editor</permission-role>
   <permission-role>Contributor</permission-role>
   <permission-role>Manager</permission-role>
  </permission-map>
  <permission-map name="liege.urban: External Reader"
                  acquired="False">
   <permission-role>Reader</permission-role>
   <permission-role>Editor</permission-role>
   <permission-role>Contributor</permission-role>
   <permission-role>Manager</permission-role>
  </permission-map>
  <permission-map name="liege.urban: Validate"
                  acquired="False">
   <permission-role>Contributor</permission-role>
   <permission-role>Manager</permission-role>
  </permission-map>
  <permission-map name="urban: Add Applicant"
                  acquired="False">
   <permission-role>Editor</permission-role>
   <permission-role>Contributor</permission-role>
   <permission-role>Manager</permission-role>
  </permission-map>
  <permission-map name="urban: Add Contact"
                  acquired="False">
   <permission-role>Editor</permission-role>
   <permission-role>Contributor</permission-role>
   <permission-role>Manager</permission-role>
  </permission-map>
  <permission-map name="urban: Add Corporation"
                  acquired="False">
   <permission-role>Editor</permission-role>
   <permission-role>Contributor</permission-role>
   <permission-role>Manager</permission-role>
  </permission-map>
  <permission-map name="urban: Add PortionOut"
                  acquired="False">
   <permission-role>AddressEditor</permission-role>
   <permission-role>Manager</permission-role>
  </permission-map>
  <permission-map name="urban: Add UrbanEvent"
                  acquired="False">
   <permission-role>Editor</permission-role>
   <permission-role>Contributor</permission-role>
   <permission-role>Manager</permission-role>
  </permission-map>
 </state>
 <state state_id="defavorable"
        title="defavorable"
        i18n:attributes="title">
  <exit-transition transition_id="go_back_4"/>
  <permission-map name="Access contents information"
                  acquired="False">
   <permission-role>Reader</permission-role>
   <permission-role>Editor</permission-role>
   <permission-role>Contributor</permission-role>
   <permission-role>Manager</permission-role>
  </permission-map>
  <permission-map name="ATContentTypes: Add File"
                  acquired="False">
   <permission-role>Editor</permission-role>
   <permission-role>Contributor</permission-role>
   <permission-role>Manager</permission-role>
  </permission-map>
  <permission-map name="ATContentTypes: Add Image"
                  acquired="False">
   <permission-role>Editor</permission-role>
   <permission-role>Contributor</permission-role>
   <permission-role>Manager</permission-role>
  </permission-map>
  <permission-map name="Add portal content"
                  acquired="False">
   <permission-role>Editor</permission-role>
   <permission-role>Contributor</permission-role>
   <permission-role>Manager</permission-role>
  </permission-map>
  <permission-map name="Delete objects"
                  acquired="False">
   <permission-role>Editor</permission-role>
   <permission-role>Contributor</permission-role>
   <permission-role>Manager</permission-role>
  </permission-map>
  <permission-map name="Modify portal content"
                  acquired="False">
   <permission-role>Editor</permission-role>
   <permission-role>Contributor</permission-role>
   <permission-role>Manager</permission-role>
  </permission-map>
  <permission-map name="View"
                  acquired="False">
   <permission-role>Reader</permission-role>
   <permission-role>Editor</permission-role>
   <permission-role>Contributor</permission-role>
   <permission-role>Manager</permission-role>
  </permission-map>
  <permission-map name="liege.urban: External Reader"
                  acquired="False">
   <permission-role>Reader</permission-role>
   <permission-role>Editor</permission-role>
   <permission-role>Contributor</permission-role>
   <permission-role>Manager</permission-role>
  </permission-map>
  <permission-map name="liege.urban: Validate"
                  acquired="False">
   <permission-role>Contributor</permission-role>
   <permission-role>Manager</permission-role>
  </permission-map>
  <permission-map name="urban: Add Applicant"
                  acquired="False">
   <permission-role>Editor</permission-role>
   <permission-role>Contributor</permission-role>
   <permission-role>Manager</permission-role>
  </permission-map>
  <permission-map name="urban: Add Contact"
                  acquired="False">
   <permission-role>Editor</permission-role>
   <permission-role>Contributor</permission-role>
   <permission-role>Manager</permission-role>
  </permission-map>
  <permission-map name="urban: Add Corporation"
                  acquired="False">
   <permission-role>Editor</permission-role>
   <permission-role>Contributor</permission-role>
   <permission-role>Manager</permission-role>
  </permission-map>
  <permission-map name="urban: Add PortionOut"
                  acquired="False">
   <permission-role>AddressEditor</permission-role>
   <permission-role>Manager</permission-role>
  </permission-map>
  <permission-map name="urban: Add UrbanEvent"
                  acquired="False">
   <permission-role>Editor</permission-role>
   <permission-role>Contributor</permission-role>
   <permission-role>Manager</permission-role>
  </permission-map>
 </state>
 <state state_id="deposit"
        title="deposit"
        i18n:attributes="title">
  <exit-transition transition_id="to_analyse"/>
  <permission-map name="Access contents information"
                  acquired="False">
   <permission-role>Reader</permission-role>
   <permission-role>Editor</permission-role>
   <permission-role>Contributor</permission-role>
   <permission-role>Manager</permission-role>
  </permission-map>
  <permission-map name="ATContentTypes: Add File"
                  acquired="False">
   <permission-role>Editor</permission-role>
   <permission-role>Contributor</permission-role>
   <permission-role>Manager</permission-role>
  </permission-map>
  <permission-map name="ATContentTypes: Add Image"
                  acquired="False">
   <permission-role>Editor</permission-role>
   <permission-role>Contributor</permission-role>
   <permission-role>Manager</permission-role>
  </permission-map>
  <permission-map name="Add portal content"
                  acquired="False">
   <permission-role>Editor</permission-role>
   <permission-role>Contributor</permission-role>
   <permission-role>Manager</permission-role>
  </permission-map>
  <permission-map name="Delete objects"
                  acquired="False">
   <permission-role>Editor</permission-role>
   <permission-role>Contributor</permission-role>
   <permission-role>Manager</permission-role>
  </permission-map>
  <permission-map name="Modify portal content"
                  acquired="False">
   <permission-role>Editor</permission-role>
   <permission-role>Contributor</permission-role>
   <permission-role>Manager</permission-role>
  </permission-map>
  <permission-map name="View"
                  acquired="False">
   <permission-role>Reader</permission-role>
   <permission-role>Editor</permission-role>
   <permission-role>Contributor</permission-role>
   <permission-role>Manager</permission-role>
  </permission-map>
  <permission-map name="liege.urban: External Reader"
                  acquired="False">
   <permission-role>Reader</permission-role>
   <permission-role>Editor</permission-role>
   <permission-role>Contributor</permission-role>
   <permission-role>Manager</permission-role>
  </permission-map>
  <permission-map name="liege.urban: Validate"
                  acquired="False">
   <permission-role>Contributor</permission-role>
   <permission-role>Manager</permission-role>
  </permission-map>
  <permission-map name="urban: Add Applicant"
                  acquired="False">
   <permission-role>Editor</permission-role>
   <permission-role>Contributor</permission-role>
   <permission-role>Manager</permission-role>
  </permission-map>
  <permission-map name="urban: Add Contact"
                  acquired="False">
   <permission-role>Editor</permission-role>
   <permission-role>Contributor</permission-role>
   <permission-role>Manager</permission-role>
  </permission-map>
  <permission-map name="urban: Add Corporation"
                  acquired="False">
   <permission-role>Editor</permission-role>
   <permission-role>Contributor</permission-role>
   <permission-role>Manager</permission-role>
  </permission-map>
  <permission-map name="urban: Add PortionOut"
                  acquired="False">
   <permission-role>AddressEditor</permission-role>
   <permission-role>Manager</permission-role>
  </permission-map>
  <permission-map name="urban: Add UrbanEvent"
                  acquired="False">
   <permission-role>Editor</permission-role>
   <permission-role>Contributor</permission-role>
   <permission-role>Manager</permission-role>
  </permission-map>
 </state>
 <state state_id="favorable"
        title="favorable"
        i18n:attributes="title">
  <exit-transition transition_id="go_back_3"/>
  <permission-map name="Access contents information"
                  acquired="False">
   <permission-role>Reader</permission-role>
   <permission-role>Editor</permission-role>
   <permission-role>Contributor</permission-role>
   <permission-role>Manager</permission-role>
  </permission-map>
  <permission-map name="ATContentTypes: Add File"
                  acquired="False">
   <permission-role>Editor</permission-role>
   <permission-role>Contributor</permission-role>
   <permission-role>Manager</permission-role>
  </permission-map>
  <permission-map name="ATContentTypes: Add Image"
                  acquired="False">
   <permission-role>Editor</permission-role>
   <permission-role>Contributor</permission-role>
   <permission-role>Manager</permission-role>
  </permission-map>
  <permission-map name="Add portal content"
                  acquired="False">
   <permission-role>Editor</permission-role>
   <permission-role>Contributor</permission-role>
   <permission-role>Manager</permission-role>
  </permission-map>
  <permission-map name="Delete objects"
                  acquired="False">
   <permission-role>Editor</permission-role>
   <permission-role>Contributor</permission-role>
   <permission-role>Manager</permission-role>
  </permission-map>
  <permission-map name="Modify portal content"
                  acquired="False">
   <permission-role>Editor</permission-role>
   <permission-role>Contributor</permission-role>
   <permission-role>Manager</permission-role>
  </permission-map>
  <permission-map name="View"
                  acquired="False">
   <permission-role>Reader</permission-role>
   <permission-role>Editor</permission-role>
   <permission-role>Contributor</permission-role>
   <permission-role>Manager</permission-role>
  </permission-map>
  <permission-map name="liege.urban: External Reader"
                  acquired="False">
   <permission-role>Reader</permission-role>
   <permission-role>Editor</permission-role>
   <permission-role>Contributor</permission-role>
   <permission-role>Manager</permission-role>
  </permission-map>
  <permission-map name="liege.urban: Validate"
                  acquired="False">
   <permission-role>Contributor</permission-role>
   <permission-role>Manager</permission-role>
  </permission-map>
  <permission-map name="urban: Add Applicant"
                  acquired="False">
   <permission-role>Editor</permission-role>
   <permission-role>Contributor</permission-role>
   <permission-role>Manager</permission-role>
  </permission-map>
  <permission-map name="urban: Add Contact"
                  acquired="False">
   <permission-role>Editor</permission-role>
   <permission-role>Contributor</permission-role>
   <permission-role>Manager</permission-role>
  </permission-map>
  <permission-map name="urban: Add Corporation"
                  acquired="False">
   <permission-role>Editor</permission-role>
   <permission-role>Contributor</permission-role>
   <permission-role>Manager</permission-role>
  </permission-map>
  <permission-map name="urban: Add PortionOut"
                  acquired="False">
   <permission-role>AddressEditor</permission-role>
   <permission-role>Manager</permission-role>
  </permission-map>
  <permission-map name="urban: Add UrbanEvent"
                  acquired="False">
   <permission-role>Editor</permission-role>
   <permission-role>Contributor</permission-role>
   <permission-role>Manager</permission-role>
  </permission-map>
 </state>
 <transition transition_id="close_defavorable"
             title="close_defavorable"
             new_state="defavorable"
             trigger="USER"
             before_script=""
             after_script=""
             i18n:attributes="title">
  <action url="" icon="" category="workflow" i18n:translate="">close_defavorable</action>
  <guard>
  </guard>
 </transition>
 <transition transition_id="close_favorable"
             title="close_favorable"
             new_state="favorable"
             trigger="USER"
             before_script=""
             after_script=""
             i18n:attributes="title">
  <action url="" icon="" category="workflow" i18n:translate="">close_favorable</action>
  <guard>
  </guard>
 </transition>
 <transition transition_id="go_back_1"
             title="go_back_1"
             new_state="deposit"
             trigger="USER"
             before_script=""
             after_script=""
             i18n:attributes="title">
  <action url="" icon="" category="workflow" i18n:translate="">go_back_1</action>
  <guard>
    <guard-permission>Manage portal content</guard-permission>
  </guard>
 </transition>
 <transition transition_id="go_back_2"
             title="go_back_2"
             new_state="analysis_validation"
             trigger="USER"
             before_script=""
             after_script=""
             i18n:attributes="title">
  <action url="" icon="" category="workflow" i18n:translate="">go_back_2</action>
  <guard>
    <guard-permission>Manage portal content</guard-permission>
  </guard>
 </transition>
 <transition transition_id="go_back_3"
             title="go_back_3"
             new_state="college"
             trigger="USER"
             before_script=""
             after_script=""
             i18n:attributes="title">
  <action url="" icon="" category="workflow" i18n:translate="">go_back_3</action>
  <guard>
    <guard-permission>Manage portal content</guard-permission>
  </guard>
 </transition>
 <transition transition_id="go_back_4"
             title="go_back_4"
             new_state="college"
             trigger="USER"
             before_script=""
             after_script=""
             i18n:attributes="title">
  <action url="" icon="" category="workflow" i18n:translate="">go_back_4</action>
  <guard>
    <guard-permission>Manage portal content</guard-permission>
  </guard>
 </transition>
 <transition transition_id="propose_analysis"
             title="propose_analysis"
             new_state="analysis_validation"
             trigger="USER"
             before_script=""
             after_script=""
             i18n:attributes="title">
  <action url="" icon="" category="workflow" i18n:translate="">propose_analysis</action>
  <guard>
    <guard-permission>Modify portal content</guard-permission>
  </guard>
 </transition>
 <transition transition_id="refuse_analysis"
             title="refuse_analysis"
             new_state="analysis"
             trigger="USER"
             before_script=""
             after_script=""
             i18n:attributes="title">
  <action url="" icon="" category="workflow" i18n:translate="">refuse_analysis</action>
  <guard>
    <guard-permission>liege.urban: Validate</guard-permission>
  </guard>
 </transition>
 <transition transition_id="to_analyse"
             title="to_analyse"
             new_state="analysis"
             trigger="USER"
             before_script=""
             after_script=""
             i18n:attributes="title">
  <action url="" icon="" category="workflow" i18n:translate="">to_analyse</action>
  <guard>
    <guard-permission>Modify portal content</guard-permission>
  </guard>
 </transition>
 <transition transition_id="validate"
             title="validate"
             new_state="college"
             trigger="USER"
             before_script=""
             after_script=""
             i18n:attributes="title">
  <action url="" icon="" category="workflow" i18n:translate="">validate</action>
  <guard>
    <guard-permission>liege.urban: Validate</guard-permission>
  </guard>
 </transition>
 <variable variable_id="action" for_catalog="False"
           for_status="True" update_always="True">
  <description>The last transition</description>
  <default>
   <expression>transition/getId|nothing</expression>
  </default>
  <guard>
  </guard>
 </variable>
 <variable variable_id="actor" for_catalog="False"
           for_status="True" update_always="True">
  <description>The ID of the user who performed the last transition</description>
  <default>
   <expression>user/getId</expression>
  </default>
  <guard>
  </guard>
 </variable>
 <variable variable_id="comments" for_catalog="False"
           for_status="True" update_always="True">
  <description>Comments about the last transition</description>
  <default>
   <expression>python:state_change.kwargs.get('comment', '')</expression>
  </default>
  <guard>
  </guard>
 </variable>
 <variable variable_id="review_history" for_catalog="False"
           for_status="False" update_always="False">
  <description>Provides access to workflow history</description>
  <default>
   <expression>state_change/getHistory</expression>
  </default>
  <guard>
   <guard-permission>Request review</guard-permission>
   <guard-permission>Review portal content</guard-permission>
  </guard>
 </variable>
 <variable variable_id="time" for_catalog="False"
           for_status="True" update_always="True">
  <description>Time of the last transition</description>
  <default>
   <expression>state_change/getDateTime</expression>
  </default>
  <guard>
  </guard>
 </variable>
<!-- ##code-section FOOT -->
<!-- ##/code-section FOOT -->
 <!-- We dont use workflow scripts any more, we use subscribers -->
</dc-workflow>
